trame/__init__.py
trame/modules/__init__.py
trame/modules/iframe.py
trame/widgets/__init__.py
trame/widgets/iframe.py
trame_iframe/__init__.py
trame_iframe/module/__init__.py
trame_iframe/module/serve/trame-iframe.mjs
trame_iframe/module/serve/trame-iframe.umd.js
trame_iframe/widgets/__init__.py
trame_iframe/widgets/iframe.py
trame_iframe-1.1.1.dist-info/LICENSE
trame_iframe-1.1.1.dist-info/METADATA
trame_iframe-1.1.1.dist-info/WHEEL
trame_iframe-1.1.1.dist-info/top_level.txt
trame_iframe-1.1.1.dist-info/RECORD
